MANIFEST.in
README.rst
setup.py
refactored/__init__.py
refactored/unittest.py
refactored.egg-info/PKG-INFO
refactored.egg-info/SOURCES.txt
refactored.egg-info/dependency_links.txt
refactored.egg-info/not-zip-safe
refactored.egg-info/requires.txt
refactored.egg-info/top_level.txt