Metadata-Version: 1.0
Name: refactored
Version: 0.3
Summary: refactored unittesting library
Home-page: https://github.com/colaberry/rfvalidator
Author: refactored
Author-email: refactored@colaberry.com
License: LICENCE
Platform: UNKNOWN
